Metadata-Version: 2.1
Name: tfsolver
Version: 1.0.1
Summary: A numerical Python toolkit for parallel electromagnetic calculation of planar multilayer thin films at multi-wavelength and multi-angle
Home-page: https://github.com/xiuguochen/tfsolver
Author: xiuguochen
Author-email: xiuguochen@hust.edu.cn
Keywords: optics,multilayer thin film,python
Classifier: License :: OSI Approved :: GNU General Public License v3 (GPLv3)
Classifier: Intended Audience :: Science/Research
License-File: LICENSE.txt
